agatha_protobuf/analysis/analysis_pb2.py
agatha_protobuf/analysis/analysis_pb2.pyi
agatha_protobuf/analysis/analysis_pb2_grpc.py
agatha_protobuf/analysis/chat_pb2.py
agatha_protobuf/analysis/chat_pb2.pyi
agatha_protobuf/analysis/chat_pb2_grpc.py
agatha_protobuf-1.0.62.dist-info/METADATA
agatha_protobuf-1.0.62.dist-info/WHEEL
agatha_protobuf-1.0.62.dist-info/top_level.txt
agatha_protobuf-1.0.62.dist-info/RECORD
