Metadata-Version: 2.4
Name: agatha-protobuf
Version: 1.0.62
Summary: Protobuf files for Agatha project
Classifier: Programming Language :: Python :: 3
Classifier: Operating System :: OS Independent
Requires-Python: >=3.8
Requires-Dist: grpcio
Requires-Dist: protobuf
